{
  "sports-card-capstone-card-data": [
    {
      "PutRequest": {
        "Item": {
          "cardId": {
            "S": "0d883399-23c2-4a77-a041-34978574cca0"
          },
          "player": {
            "S": "Jayson Tatum"
          },
          "card_name": {
            "S": "Jayson Tatum 2025 Topps Chrome #RS-1 Rock Stars"
          },
          "grade": {
            "S": "Raw"
          },
          "date": {
            "S": "20260210"
          },
          "price": {
            "N": "31.75"
          },
          "number_of_sales": {
            "N": "5"
          },
          "total_sales_amount": {
            "N": "217.75"
          },
          "price_change_percent": {
            "N": "-29.44"
          },
          "average_price": {
            "N": "43.55"
          },
          "volume_change_percent": {
            "N": "-54.55"
          },
          "price_change_amount": {
            "N": "-13.25"
          },
          "max_sale_price": {
            "N": "52.00"
          },
          "min_sale_price": {
            "N": "31.75"
          },
          "last_sale_date": {
            "S": "02/09/2026"
          }
        }
      }
    },
    {
      "PutRequest": {
        "Item": {
          "cardId": {
            "S": "9d2d64f2-6009-4d79-99e3-04f02e9dd86e"
          },
          "player": {
            "S": "Isaiah Collier"
          },
          "card_name": {
            "S": "Isaiah Collier 2024 Prizm #227 Fast Break"
          },
          "grade": {
            "S": "Raw"
          },
          "date": {
            "S": "20260210"
          },
          "price": {
            "N": "3.25"
          },
          "number_of_sales": {
            "N": "5"
          },
          "total_sales_amount": {
            "N": "23.96"
          },
          "price_change_percent": {
            "N": "-29.50"
          },
          "average_price": {
            "N": "4.79"
          },
          "volume_change_percent": {
            "N": "0.00"
          },
          "price_change_amount": {
            "N": "-1.36"
          },
          "max_sale_price": {
            "N": "8.50"
          },
          "min_sale_price": {
            "N": "2.99"
          },
          "last_sale_date": {
            "S": "02/09/2026"
          }
        }
      }
    },
    {
      "PutRequest": {
        "Item": {
          "cardId": {
            "S": "6852d0d8-2316-475e-b60d-7704a4d01c3b"
          },
          "player": {
            "S": "Drake Maye"
          },
          "card_name": {
            "S": "Drake Maye 2024 Select #218 Club Level"
          },
          "grade": {
            "S": "Raw"
          },
          "date": {
            "S": "20260210"
          },
          "price": {
            "N": "2.72"
          },
          "number_of_sales": {
            "N": "81"
          },
          "total_sales_amount": {
            "N": "339.87"
          },
          "price_change_percent": {
            "N": "-29.57"
          },
          "average_price": {
            "N": "4.20"
          },
          "volume_change_percent": {
            "N": "-18.18"
          },
          "price_change_amount": {
            "N": "-1.14"
          },
          "max_sale_price": {
            "N": "16.00"
          },
          "min_sale_price": {
            "N": "0.99"
          },
          "last_sale_date": {
            "S": "02/09/2026"
          }
        }
      }
    },
    {
      "PutRequest": {
        "Item": {
          "cardId": {
            "S": "6266c9bb-ba71-441a-92aa-4536636f26ee"
          },
          "player": {
            "S": "Cedric Coward"
          },
          "card_name": {
            "S": "Cedric Coward 2025 Topps Chrome #261 Red White & Blue Refractor"
          },
          "grade": {
            "S": "Raw"
          },
          "date": {
            "S": "20260210"
          },
          "price": {
            "N": "3.58"
          },
          "number_of_sales": {
            "N": "24"
          },
          "total_sales_amount": {
            "N": "104.46"
          },
          "price_change_percent": {
            "N": "-29.57"
          },
          "average_price": {
            "N": "4.35"
          },
          "volume_change_percent": {
            "N": "-20.00"
          },
          "price_change_amount": {
            "N": "-1.50"
          },
          "max_sale_price": {
            "N": "7.68"
          },
          "min_sale_price": {
            "N": "2.26"
          },
          "last_sale_date": {
            "S": "02/08/2026"
          }
        }
      }
    },
    {
      "PutRequest": {
        "Item": {
          "cardId": {
            "S": "95fe83c8-6e2e-4504-880a-ef2e9d438698"
          },
          "player": {
            "S": "Vinnie Johnson"
          },
          "card_name": {
            "S": "Vinnie Johnson 1986 Fleer #56 Base"
          },
          "grade": {
            "S": "Raw"
          },
          "date": {
            "S": "20260210"
          },
          "price": {
            "N": "4.50"
          },
          "number_of_sales": {
            "N": "7"
          },
          "total_sales_amount": {
            "N": "35.93"
          },
          "price_change_percent": {
            "N": "-29.58"
          },
          "average_price": {
            "N": "5.13"
          },
          "volume_change_percent": {
            "N": "-12.50"
          },
          "price_change_amount": {
            "N": "-1.89"
          },
          "max_sale_price": {
            "N": "6.39"
          },
          "min_sale_price": {
            "N": "2.99"
          },
          "last_sale_date": {
            "S": "02/08/2026"
          }
        }
      }
    },
    {
      "PutRequest": {
        "Item": {
          "cardId": {
            "S": "7677db4f-715c-486b-b5f0-112b8f7bdf1b"
          },
          "player": {
            "S": "Michael Jordan"
          },
          "card_name": {
            "S": "Michael Jordan 1992 Upper Deck #AW1 Award Winner Holograms (Low Series)"
          },
          "grade": {
            "S": "Raw"
          },
          "date": {
            "S": "20260210"
          },
          "price": {
            "N": "8.63"
          },
          "number_of_sales": {
            "N": "13"
          },
          "total_sales_amount": {
            "N": "133.75"
          },
          "price_change_percent": {
            "N": "-29.59"
          },
          "average_price": {
            "N": "10.29"
          },
          "volume_change_percent": {
            "N": "8.33"
          },
          "price_change_amount": {
            "N": "-3.63"
          },
          "max_sale_price": {
            "N": "19.99"
          },
          "min_sale_price": {
            "N": "0.99"
          },
          "last_sale_date": {
            "S": "02/09/2026"
          }
        }
      }
    },
    {
      "PutRequest": {
        "Item": {
          "cardId": {
            "S": "600c4ead-47cf-43a5-bc11-8e791276fc99"
          },
          "player": {
            "S": "Luka Doncic"
          },
          "card_name": {
            "S": "Luka Doncic 2018 Hoops #268 Base"
          },
          "grade": {
            "S": "PSA 9"
          },
          "date": {
            "S": "20260210"
          },
          "price": {
            "N": "32.00"
          },
          "number_of_sales": {
            "N": "5"
          },
          "total_sales_amount": {
            "N": "193.45"
          },
          "price_change_percent": {
            "N": "-29.59"
          },
          "average_price": {
            "N": "38.69"
          },
          "volume_change_percent": {
            "N": "0.00"
          },
          "price_change_amount": {
            "N": "-13.45"
          },
          "max_sale_price": {
            "N": "45.45"
          },
          "min_sale_price": {
            "N": "32.00"
          },
          "last_sale_date": {
            "S": "02/07/2026"
          }
        }
      }
    },
    {
      "PutRequest": {
        "Item": {
          "cardId": {
            "S": "6d1a08bb-15d6-4183-9852-e0ec74e09002"
          },
          "player": {
            "S": "Jayden Daniels"
          },
          "card_name": {
            "S": "Jayden Daniels 2024 Select #112 Premier Level Black & Red Shock"
          },
          "grade": {
            "S": "Raw"
          },
          "date": {
            "S": "20260210"
          },
          "price": {
            "N": "5.50"
          },
          "number_of_sales": {
            "N": "12"
          },
          "total_sales_amount": {
            "N": "84.91"
          },
          "price_change_percent": {
            "N": "-29.60"
          },
          "average_price": {
            "N": "7.08"
          },
          "volume_change_percent": {
            "N": "20.00"
          },
          "price_change_amount": {
            "N": "-2.31"
          },
          "max_sale_price": {
            "N": "12.50"
          },
          "min_sale_price": {
            "N": "5.00"
          },
          "last_sale_date": {
            "S": "02/06/2026"
          }
        }
      }
    },
    {
      "PutRequest": {
        "Item": {
          "cardId": {
            "S": "6f0b968c-6cdb-4d7c-8ba4-0293a1e6c26e"
          },
          "player": {
            "S": "Victor Wembanyama"
          },
          "card_name": {
            "S": "Victor Wembanyama 2023 Prizm #2 Global Reach"
          },
          "grade": {
            "S": "Raw"
          },
          "date": {
            "S": "20260210"
          },
          "price": {
            "N": "2.99"
          },
          "number_of_sales": {
            "N": "11"
          },
          "total_sales_amount": {
            "N": "44.71"
          },
          "price_change_percent": {
            "N": "-29.65"
          },
          "average_price": {
            "N": "4.06"
          },
          "volume_change_percent": {
            "N": "-26.67"
          },
          "price_change_amount": {
            "N": "-1.26"
          },
          "max_sale_price": {
            "N": "7.33"
          },
          "min_sale_price": {
            "N": "2.90"
          },
          "last_sale_date": {
            "S": "02/09/2026"
          }
        }
      }
    },
    {
      "PutRequest": {
        "Item": {
          "cardId": {
            "S": "9cf2181c-7d96-4603-86d6-9b0d731fdd64"
          },
          "player": {
            "S": "Drake Maye"
          },
          "card_name": {
            "S": "Drake Maye 2024 Origins #12 Original Gridiron"
          },
          "grade": {
            "S": "Raw"
          },
          "date": {
            "S": "20260210"
          },
          "price": {
            "N": "22.50"
          },
          "number_of_sales": {
            "N": "8"
          },
          "total_sales_amount": {
            "N": "278.26"
          },
          "price_change_percent": {
            "N": "-29.69"
          },
          "average_price": {
            "N": "34.78"
          },
          "volume_change_percent": {
            "N": "166.67"
          },
          "price_change_amount": {
            "N": "-9.50"
          },
          "max_sale_price": {
            "N": "42.01"
          },
          "min_sale_price": {
            "N": "22.50"
          },
          "last_sale_date": {
            "S": "02/09/2026"
          }
        }
      }
    },
    {
      "PutRequest": {
        "Item": {
          "cardId": {
            "S": "57b9da34-a7b5-4326-80fa-794376e6b77c"
          },
          "player": {
            "S": "Dillon Gabriel"
          },
          "card_name": {
            "S": "Dillon Gabriel 2025 Donruss #316 Rated Rookie Autographs - Green"
          },
          "grade": {
            "S": "Raw"
          },
          "date": {
            "S": "20260210"
          },
          "price": {
            "N": "8.00"
          },
          "number_of_sales": {
            "N": "5"
          },
          "total_sales_amount": {
            "N": "43.76"
          },
          "price_change_percent": {
            "N": "-29.70"
          },
          "average_price": {
            "N": "8.75"
          },
          "volume_change_percent": {
            "N": "66.67"
          },
          "price_change_amount": {
            "N": "-3.38"
          },
          "max_sale_price": {
            "N": "12.76"
          },
          "min_sale_price": {
            "N": "5.00"
          },
          "last_sale_date": {
            "S": "02/08/2026"
          }
        }
      }
    },
    {
      "PutRequest": {
        "Item": {
          "cardId": {
            "S": "731970bf-aec3-44e1-a32d-b1f4bb5d3860"
          },
          "player": {
            "S": "Drake Maye"
          },
          "card_name": {
            "S": "Drake Maye 2024 Topps Signature Class #152 Base"
          },
          "grade": {
            "S": "Raw"
          },
          "date": {
            "S": "20260210"
          },
          "price": {
            "N": "1.76"
          },
          "number_of_sales": {
            "N": "30"
          },
          "total_sales_amount": {
            "N": "102.37"
          },
          "price_change_percent": {
            "N": "-29.71"
          },
          "average_price": {
            "N": "3.41"
          },
          "volume_change_percent": {
            "N": "25.00"
          },
          "price_change_amount": {
            "N": "-0.74"
          },
          "max_sale_price": {
            "N": "6.95"
          },
          "min_sale_price": {
            "N": "0.99"
          },
          "last_sale_date": {
            "S": "02/09/2026"
          }
        }
      }
    },
    {
      "PutRequest": {
        "Item": {
          "cardId": {
            "S": "be940dfb-48f8-4d25-80a0-d799ec44c126"
          },
          "player": {
            "S": "Emmitt Smith"
          },
          "card_name": {
            "S": "Emmitt Smith 1990 Pro Set #685 Base"
          },
          "grade": {
            "S": "Raw"
          },
          "date": {
            "S": "20260210"
          },
          "price": {
            "N": "1.28"
          },
          "number_of_sales": {
            "N": "26"
          },
          "total_sales_amount": {
            "N": "89.87"
          },
          "price_change_percent": {
            "N": "-29.80"
          },
          "average_price": {
            "N": "3.46"
          },
          "volume_change_percent": {
            "N": "-44.68"
          },
          "price_change_amount": {
            "N": "-0.54"
          },
          "max_sale_price": {
            "N": "20.00"
          },
          "min_sale_price": {
            "N": "0.99"
          },
          "last_sale_date": {
            "S": "02/09/2026"
          }
        }
      }
    },
    {
      "PutRequest": {
        "Item": {
          "cardId": {
            "S": "b5ffd37c-5a69-4853-bf2a-380a8338568c"
          },
          "player": {
            "S": "Joe Burrow"
          },
          "card_name": {
            "S": "Joe Burrow 2020 Donruss #301 Base"
          },
          "grade": {
            "S": "Raw"
          },
          "date": {
            "S": "20260210"
          },
          "price": {
            "N": "7.02"
          },
          "number_of_sales": {
            "N": "9"
          },
          "total_sales_amount": {
            "N": "96.01"
          },
          "price_change_percent": {
            "N": "-29.80"
          },
          "average_price": {
            "N": "10.67"
          },
          "volume_change_percent": {
            "N": "12.50"
          },
          "price_change_amount": {
            "N": "-2.98"
          },
          "max_sale_price": {
            "N": "12.99"
          },
          "min_sale_price": {
            "N": "6.00"
          },
          "last_sale_date": {
            "S": "02/09/2026"
          }
        }
      }
    },
    {
      "PutRequest": {
        "Item": {
          "cardId": {
            "S": "15789f3d-a970-4da1-92df-d7d6d9690c3e"
          },
          "player": {
            "S": "Caleb Williams"
          },
          "card_name": {
            "S": "Caleb Williams 2024 Optic #201 Base"
          },
          "grade": {
            "S": "Raw"
          },
          "date": {
            "S": "20260210"
          },
          "price": {
            "N": "3.18"
          },
          "number_of_sales": {
            "N": "77"
          },
          "total_sales_amount": {
            "N": "272.35"
          },
          "price_change_percent": {
            "N": "-29.80"
          },
          "average_price": {
            "N": "3.54"
          },
          "volume_change_percent": {
            "N": "-13.48"
          },
          "price_change_amount": {
            "N": "-1.35"
          },
          "max_sale_price": {
            "N": "20.00"
          },
          "min_sale_price": {
            "N": "0.99"
          },
          "last_sale_date": {
            "S": "02/09/2026"
          }
        }
      }
    },
    {
      "PutRequest": {
        "Item": {
          "cardId": {
            "S": "19f89442-10fb-4a04-87d4-a7d73d9298b0"
          },
          "player": {
            "S": "Kon Knueppel"
          },
          "card_name": {
            "S": "Kon Knueppel 2025 Topps Chrome #INS-14 Instinct - Refractor"
          },
          "grade": {
            "S": "Raw"
          },
          "date": {
            "S": "20260210"
          },
          "price": {
            "N": "13.22"
          },
          "number_of_sales": {
            "N": "11"
          },
          "total_sales_amount": {
            "N": "183.62"
          },
          "price_change_percent": {
            "N": "-29.80"
          },
          "average_price": {
            "N": "16.69"
          },
          "volume_change_percent": {
            "N": "22.22"
          },
          "price_change_amount": {
            "N": "-5.62"
          },
          "max_sale_price": {
            "N": "24.99"
          },
          "min_sale_price": {
            "N": "10.00"
          },
          "last_sale_date": {
            "S": "02/09/2026"
          }
        }
      }
    },
    {
      "PutRequest": {
        "Item": {
          "cardId": {
            "S": "c7d9a06a-337e-4b74-b341-4f455201134a"
          },
          "player": {
            "S": "Cam Skattebo"
          },
          "card_name": {
            "S": "Cam Skattebo 2025 Donruss #302 Optic Preview - Red Pandora"
          },
          "grade": {
            "S": "Raw"
          },
          "date": {
            "S": "20260210"
          },
          "price": {
            "N": "18.50"
          },
          "number_of_sales": {
            "N": "7"
          },
          "total_sales_amount": {
            "N": "127.46"
          },
          "price_change_percent": {
            "N": "-29.80"
          },
          "average_price": {
            "N": "18.21"
          },
          "volume_change_percent": {
            "N": "-12.50"
          },
          "price_change_amount": {
            "N": "-7.86"
          },
          "max_sale_price": {
            "N": "30.71"
          },
          "min_sale_price": {
            "N": "3.25"
          },
          "last_sale_date": {
            "S": "02/08/2026"
          }
        }
      }
    },
    {
      "PutRequest": {
        "Item": {
          "cardId": {
            "S": "95960360-65c9-415b-b3e4-32dc7b366d80"
          },
          "player": {
            "S": "Magic Johnson"
          },
          "card_name": {
            "S": "Magic Johnson 1986 Fleer Sticker #7 Base"
          },
          "grade": {
            "S": "Raw"
          },
          "date": {
            "S": "20260210"
          },
          "price": {
            "N": "25.00"
          },
          "number_of_sales": {
            "N": "8"
          },
          "total_sales_amount": {
            "N": "255.49"
          },
          "price_change_percent": {
            "N": "-29.82"
          },
          "average_price": {
            "N": "31.94"
          },
          "volume_change_percent": {
            "N": "-11.11"
          },
          "price_change_amount": {
            "N": "-10.63"
          },
          "max_sale_price": {
            "N": "43.50"
          },
          "min_sale_price": {
            "N": "25.00"
          },
          "last_sale_date": {
            "S": "02/09/2026"
          }
        }
      }
    },
    {
      "PutRequest": {
        "Item": {
          "cardId": {
            "S": "004bf086-9660-44c3-9c72-8a7dcf8e3c00"
          },
          "player": {
            "S": "Michael Jordan"
          },
          "card_name": {
            "S": "Michael Jordan 1998 Upper Deck Black Diamond #22 Base"
          },
          "grade": {
            "S": "Raw"
          },
          "date": {
            "S": "20260210"
          },
          "price": {
            "N": "4.95"
          },
          "number_of_sales": {
            "N": "9"
          },
          "total_sales_amount": {
            "N": "52.59"
          },
          "price_change_percent": {
            "N": "-29.86"
          },
          "average_price": {
            "N": "5.84"
          },
          "volume_change_percent": {
            "N": "12.50"
          },
          "price_change_amount": {
            "N": "-2.11"
          },
          "max_sale_price": {
            "N": "12.23"
          },
          "min_sale_price": {
            "N": "4.00"
          },
          "last_sale_date": {
            "S": "02/09/2026"
          }
        }
      }
    },
    {
      "PutRequest": {
        "Item": {
          "cardId": {
            "S": "92faef5a-72e7-4f01-af2b-6f36b524706d"
          },
          "player": {
            "S": "Kobe Bryant"
          },
          "card_name": {
            "S": "Kobe Bryant 1997 Fleer #4 Soaring Stars"
          },
          "grade": {
            "S": "Raw"
          },
          "date": {
            "S": "20260210"
          },
          "price": {
            "N": "47.33"
          },
          "number_of_sales": {
            "N": "7"
          },
          "total_sales_amount": {
            "N": "372.00"
          },
          "price_change_percent": {
            "N": "-29.88"
          },
          "average_price": {
            "N": "53.14"
          },
          "volume_change_percent": {
            "N": "75.00"
          },
          "price_change_amount": {
            "N": "-20.17"
          },
          "max_sale_price": {
            "N": "89.00"
          },
          "min_sale_price": {
            "N": "35.00"
          },
          "last_sale_date": {
            "S": "02/08/2026"
          }
        }
      }
    },
    {
      "PutRequest": {
        "Item": {
          "cardId": {
            "S": "ef32d90f-387a-4c93-95fc-7d27009d9da3"
          },
          "player": {
            "S": "Dennis Rodman"
          },
          "card_name": {
            "S": "Dennis Rodman 2025 Topps Chrome #RS-12 Rock Stars"
          },
          "grade": {
            "S": "Raw"
          },
          "date": {
            "S": "20260210"
          },
          "price": {
            "N": "38.55"
          },
          "number_of_sales": {
            "N": "7"
          },
          "total_sales_amount": {
            "N": "347.49"
          },
          "price_change_percent": {
            "N": "-29.89"
          },
          "average_price": {
            "N": "49.64"
          },
          "volume_change_percent": {
            "N": "-63.16"
          },
          "price_change_amount": {
            "N": "-16.44"
          },
          "max_sale_price": {
            "N": "60.00"
          },
          "min_sale_price": {
            "N": "38.55"
          },
          "last_sale_date": {
            "S": "02/09/2026"
          }
        }
      }
    },
    {
      "PutRequest": {
        "Item": {
          "cardId": {
            "S": "271f4e9f-4def-4b3e-92a6-9d9ff9f7a1cc"
          },
          "player": {
            "S": "Cooper Flagg"
          },
          "card_name": {
            "S": "Cooper Flagg 2025 Topps Chrome Sapphire Edition #251 Base"
          },
          "grade": {
            "S": "Raw"
          },
          "date": {
            "S": "20260210"
          },
          "price": {
            "N": "1025.00"
          },
          "number_of_sales": {
            "N": "15"
          },
          "total_sales_amount": {
            "N": "20982.34"
          },
          "price_change_percent": {
            "N": "-29.89"
          },
          "average_price": {
            "N": "1398.82"
          },
          "volume_change_percent": {
            "N": "-11.76"
          },
          "price_change_amount": {
            "N": "-437.00"
          },
          "max_sale_price": {
            "N": "1630.00"
          },
          "min_sale_price": {
            "N": "1025.00"
          },
          "last_sale_date": {
            "S": "02/09/2026"
          }
        }
      }
    },
    {
      "PutRequest": {
        "Item": {
          "cardId": {
            "S": "75c89d6a-9606-4f9d-8511-85ef096c2a19"
          },
          "player": {
            "S": "Drake Maye"
          },
          "card_name": {
            "S": "Drake Maye 2024 Select #27 Concourse Green & Yellow Shock"
          },
          "grade": {
            "S": "Raw"
          },
          "date": {
            "S": "20260210"
          },
          "price": {
            "N": "16.00"
          },
          "number_of_sales": {
            "N": "25"
          },
          "total_sales_amount": {
            "N": "510.13"
          },
          "price_change_percent": {
            "N": "-29.93"
          },
          "average_price": {
            "N": "20.41"
          },
          "volume_change_percent": {
            "N": "127.27"
          },
          "price_change_amount": {
            "N": "-6.83"
          },
          "max_sale_price": {
            "N": "32.00"
          },
          "min_sale_price": {
            "N": "10.50"
          },
          "last_sale_date": {
            "S": "02/09/2026"
          }
        }
      }
    },
    {
      "PutRequest": {
        "Item": {
          "cardId": {
            "S": "c8a475bf-397e-4044-a56e-af7b6f6397d2"
          },
          "player": {
            "S": "Otis Birdsong"
          },
          "card_name": {
            "S": "Otis Birdsong 1986 Fleer #10 Base"
          },
          "grade": {
            "S": "Raw"
          },
          "date": {
            "S": "20260210"
          },
          "price": {
            "N": "7.00"
          },
          "number_of_sales": {
            "N": "5"
          },
          "total_sales_amount": {
            "N": "32.53"
          },
          "price_change_percent": {
            "N": "-30.00"
          },
          "average_price": {
            "N": "6.51"
          },
          "volume_change_percent": {
            "N": "25.00"
          },
          "price_change_amount": {
            "N": "-3.00"
          },
          "max_sale_price": {
            "N": "10.00"
          },
          "min_sale_price": {
            "N": "0.99"
          },
          "last_sale_date": {
            "S": "02/08/2026"
          }
        }
      }
    },
    {
      "PutRequest": {
        "Item": {
          "cardId": {
            "S": "29dcad62-3edb-40b7-926a-7b2473a3f80e"
          },
          "player": {
            "S": "Jayden Daniels"
          },
          "card_name": {
            "S": "Jayden Daniels 2024 Prizm #PJ-JDS Premier Jerseys - Neon Green Pulsar"
          },
          "grade": {
            "S": "Raw"
          },
          "date": {
            "S": "20260210"
          },
          "price": {
            "N": "7.00"
          },
          "number_of_sales": {
            "N": "9"
          },
          "total_sales_amount": {
            "N": "76.42"
          },
          "price_change_percent": {
            "N": "-30.00"
          },
          "average_price": {
            "N": "8.49"
          },
          "volume_change_percent": {
            "N": "50.00"
          },
          "price_change_amount": {
            "N": "-3.00"
          },
          "max_sale_price": {
            "N": "11.99"
          },
          "min_sale_price": {
            "N": "4.69"
          },
          "last_sale_date": {
            "S": "02/08/2026"
          }
        }
      }
    }
  ]
}