{
  "sports-card-capstone-card-data": [
    {
      "PutRequest": {
        "Item": {
          "cardId": {
            "S": "cfa6e1c7-3114-481e-87a2-8ba20ee9d882"
          },
          "player": {
            "S": "Matthew Golden"
          },
          "card_name": {
            "S": "Matthew Golden 2025 Mosaic #285 Rookie Variation - Silver"
          },
          "grade": {
            "S": "Raw"
          },
          "date": {
            "S": "20260207"
          },
          "price": {
            "N": "2.12"
          },
          "number_of_sales": {
            "N": "50"
          },
          "total_sales_amount": {
            "N": "137.27"
          },
          "price_change_percent": {
            "N": "-81.37"
          },
          "average_price": {
            "N": "2.75"
          },
          "volume_change_percent": {
            "N": "0.00"
          },
          "price_change_amount": {
            "N": "-9.26"
          },
          "max_sale_price": {
            "N": "11.38"
          },
          "min_sale_price": {
            "N": "0.99"
          },
          "last_sale_date": {
            "S": "01/28/2026"
          }
        }
      }
    },
    {
      "PutRequest": {
        "Item": {
          "cardId": {
            "S": "b55a74b5-2fef-47b3-8883-758ac22baf27"
          },
          "player": {
            "S": "Jayden Daniels"
          },
          "card_name": {
            "S": "Jayden Daniels 2024 Prizm #347 Base"
          },
          "grade": {
            "S": "SGC 10"
          },
          "date": {
            "S": "20260207"
          },
          "price": {
            "N": "34.00"
          },
          "number_of_sales": {
            "N": "118"
          },
          "total_sales_amount": {
            "N": "6683.80"
          },
          "price_change_percent": {
            "N": "-81.37"
          },
          "average_price": {
            "N": "56.64"
          },
          "volume_change_percent": {
            "N": "3833.33"
          },
          "price_change_amount": {
            "N": "-148.50"
          },
          "max_sale_price": {
            "N": "182.50"
          },
          "min_sale_price": {
            "N": "12.50"
          },
          "last_sale_date": {
            "S": "01/31/2026"
          }
        }
      }
    },
    {
      "PutRequest": {
        "Item": {
          "cardId": {
            "S": "226498b9-8345-47f4-bbf3-abf8414354b7"
          },
          "player": {
            "S": "Bronny James Jr."
          },
          "card_name": {
            "S": "Bronny James Jr. 2024 Prizm #2 Prizmania"
          },
          "grade": {
            "S": "Raw"
          },
          "date": {
            "S": "20260207"
          },
          "price": {
            "N": "136.00"
          },
          "number_of_sales": {
            "N": "25"
          },
          "total_sales_amount": {
            "N": "8626.19"
          },
          "price_change_percent": {
            "N": "-81.37"
          },
          "average_price": {
            "N": "345.05"
          },
          "volume_change_percent": {
            "N": "0.00"
          },
          "price_change_amount": {
            "N": "-594.00"
          },
          "max_sale_price": {
            "N": "730.00"
          },
          "min_sale_price": {
            "N": "75.00"
          },
          "last_sale_date": {
            "S": "01/31/2026"
          }
        }
      }
    },
    {
      "PutRequest": {
        "Item": {
          "cardId": {
            "S": "8f4b3339-e719-47a7-8e6c-dff3b1e31119"
          },
          "player": {
            "S": "Jalen McMillan"
          },
          "card_name": {
            "S": "Jalen McMillan 2024 Prizm #338 Red"
          },
          "grade": {
            "S": "Raw"
          },
          "date": {
            "S": "20260207"
          },
          "price": {
            "N": "7.08"
          },
          "number_of_sales": {
            "N": "12"
          },
          "total_sales_amount": {
            "N": "344.35"
          },
          "price_change_percent": {
            "N": "-81.37"
          },
          "average_price": {
            "N": "28.70"
          },
          "volume_change_percent": {
            "N": "300.00"
          },
          "price_change_amount": {
            "N": "-30.92"
          },
          "max_sale_price": {
            "N": "49.95"
          },
          "min_sale_price": {
            "N": "7.08"
          },
          "last_sale_date": {
            "S": "01/24/2026"
          }
        }
      }
    },
    {
      "PutRequest": {
        "Item": {
          "cardId": {
            "S": "05137d40-b6d6-47da-aca6-c370dade11c5"
          },
          "player": {
            "S": "EJ Liddell"
          },
          "card_name": {
            "S": "EJ Liddell 2022 Donruss #ND-EJL Next Day Autographs"
          },
          "grade": {
            "S": "Raw"
          },
          "date": {
            "S": "20260207"
          },
          "price": {
            "N": "1.75"
          },
          "number_of_sales": {
            "N": "7"
          },
          "total_sales_amount": {
            "N": "34.59"
          },
          "price_change_percent": {
            "N": "-81.36"
          },
          "average_price": {
            "N": "4.94"
          },
          "volume_change_percent": {
            "N": "133.33"
          },
          "price_change_amount": {
            "N": "-7.64"
          },
          "max_sale_price": {
            "N": "9.74"
          },
          "min_sale_price": {
            "N": "1.75"
          },
          "last_sale_date": {
            "S": "01/16/2026"
          }
        }
      }
    },
    {
      "PutRequest": {
        "Item": {
          "cardId": {
            "S": "fef5ebc4-c8c4-4d59-bcb3-7231ef926403"
          },
          "player": {
            "S": "Quinn Ewers"
          },
          "card_name": {
            "S": "Quinn Ewers 2024 Prizm Draft Picks #191 Red"
          },
          "grade": {
            "S": "Raw"
          },
          "date": {
            "S": "20260207"
          },
          "price": {
            "N": "1.49"
          },
          "number_of_sales": {
            "N": "32"
          },
          "total_sales_amount": {
            "N": "180.31"
          },
          "price_change_percent": {
            "N": "-81.35"
          },
          "average_price": {
            "N": "5.63"
          },
          "volume_change_percent": {
            "N": "220.00"
          },
          "price_change_amount": {
            "N": "-6.50"
          },
          "max_sale_price": {
            "N": "12.75"
          },
          "min_sale_price": {
            "N": "0.99"
          },
          "last_sale_date": {
            "S": "01/04/2026"
          }
        }
      }
    },
    {
      "PutRequest": {
        "Item": {
          "cardId": {
            "S": "91a13cf6-8d84-437c-b8f4-4f3576df4ac6"
          },
          "player": {
            "S": "Victor Wembanyama"
          },
          "card_name": {
            "S": "Victor Wembanyama 2023 Prizm Draft Picks #1 Fireworks"
          },
          "grade": {
            "S": "Raw"
          },
          "date": {
            "S": "20260207"
          },
          "price": {
            "N": "4.01"
          },
          "number_of_sales": {
            "N": "116"
          },
          "total_sales_amount": {
            "N": "666.70"
          },
          "price_change_percent": {
            "N": "-81.35"
          },
          "average_price": {
            "N": "5.75"
          },
          "volume_change_percent": {
            "N": "-74.28"
          },
          "price_change_amount": {
            "N": "-17.49"
          },
          "max_sale_price": {
            "N": "21.50"
          },
          "min_sale_price": {
            "N": "0.99"
          },
          "last_sale_date": {
            "S": "02/05/2026"
          }
        }
      }
    },
    {
      "PutRequest": {
        "Item": {
          "cardId": {
            "S": "c943057f-d258-45c1-86b9-a5614d774374"
          },
          "player": {
            "S": "Joe Burrow"
          },
          "card_name": {
            "S": "Joe Burrow 2020 Chronicles #O-1 Omega"
          },
          "grade": {
            "S": "Raw"
          },
          "date": {
            "S": "20260207"
          },
          "price": {
            "N": "1.86"
          },
          "number_of_sales": {
            "N": "144"
          },
          "total_sales_amount": {
            "N": "481.22"
          },
          "price_change_percent": {
            "N": "-81.35"
          },
          "average_price": {
            "N": "3.34"
          },
          "volume_change_percent": {
            "N": "-22.58"
          },
          "price_change_amount": {
            "N": "-8.13"
          },
          "max_sale_price": {
            "N": "20.00"
          },
          "min_sale_price": {
            "N": "0.99"
          },
          "last_sale_date": {
            "S": "01/31/2026"
          }
        }
      }
    },
    {
      "PutRequest": {
        "Item": {
          "cardId": {
            "S": "779d9024-4f58-47a1-a77a-263cffaa0a41"
          },
          "player": {
            "S": "Brett Favre"
          },
          "card_name": {
            "S": "Brett Favre 2024 Topps Resurgence #W-24 Wired"
          },
          "grade": {
            "S": "Raw"
          },
          "date": {
            "S": "20260207"
          },
          "price": {
            "N": "6.53"
          },
          "number_of_sales": {
            "N": "13"
          },
          "total_sales_amount": {
            "N": "247.80"
          },
          "price_change_percent": {
            "N": "-81.34"
          },
          "average_price": {
            "N": "19.06"
          },
          "volume_change_percent": {
            "N": "0.00"
          },
          "price_change_amount": {
            "N": "-28.47"
          },
          "max_sale_price": {
            "N": "37.00"
          },
          "min_sale_price": {
            "N": "6.53"
          },
          "last_sale_date": {
            "S": "02/05/2026"
          }
        }
      }
    },
    {
      "PutRequest": {
        "Item": {
          "cardId": {
            "S": "fb223247-0f52-4579-994b-cd5ff72dd7c9"
          },
          "player": {
            "S": "Bradley Beal"
          },
          "card_name": {
            "S": "Bradley Beal 2023 Select #247 Courtside Elephant"
          },
          "grade": {
            "S": "Raw"
          },
          "date": {
            "S": "20260207"
          },
          "price": {
            "N": "5.60"
          },
          "number_of_sales": {
            "N": "9"
          },
          "total_sales_amount": {
            "N": "231.80"
          },
          "price_change_percent": {
            "N": "-81.33"
          },
          "average_price": {
            "N": "25.76"
          },
          "volume_change_percent": {
            "N": "200.00"
          },
          "price_change_amount": {
            "N": "-24.40"
          },
          "max_sale_price": {
            "N": "39.20"
          },
          "min_sale_price": {
            "N": "5.60"
          },
          "last_sale_date": {
            "S": "10/25/2025"
          }
        }
      }
    },
    {
      "PutRequest": {
        "Item": {
          "cardId": {
            "S": "2a526409-09e5-4661-bf0b-795d52457b74"
          },
          "player": {
            "S": "Michael Penix Jr."
          },
          "card_name": {
            "S": "Michael Penix Jr. 2024 Prizm #378 Blue Sparkle"
          },
          "grade": {
            "S": "Raw"
          },
          "date": {
            "S": "20260207"
          },
          "price": {
            "N": "98.00"
          },
          "number_of_sales": {
            "N": "14"
          },
          "total_sales_amount": {
            "N": "4173.44"
          },
          "price_change_percent": {
            "N": "-81.33"
          },
          "average_price": {
            "N": "298.10"
          },
          "volume_change_percent": {
            "N": "0.00"
          },
          "price_change_amount": {
            "N": "-427.00"
          },
          "max_sale_price": {
            "N": "525.00"
          },
          "min_sale_price": {
            "N": "90.00"
          },
          "last_sale_date": {
            "S": "01/06/2026"
          }
        }
      }
    },
    {
      "PutRequest": {
        "Item": {
          "cardId": {
            "S": "457710e4-8882-48ee-b00a-3ce7325dc9ee"
          },
          "player": {
            "S": "Deandre Ayton"
          },
          "card_name": {
            "S": "Deandre Ayton 2018 Prizm #1 Emergent"
          },
          "grade": {
            "S": "PSA 9"
          },
          "date": {
            "S": "20260207"
          },
          "price": {
            "N": "2.80"
          },
          "number_of_sales": {
            "N": "5"
          },
          "total_sales_amount": {
            "N": "25.63"
          },
          "price_change_percent": {
            "N": "-81.33"
          },
          "average_price": {
            "N": "5.13"
          },
          "volume_change_percent": {
            "N": "150.00"
          },
          "price_change_amount": {
            "N": "-12.20"
          },
          "max_sale_price": {
            "N": "15.00"
          },
          "min_sale_price": {
            "N": "0.99"
          },
          "last_sale_date": {
            "S": "07/16/2025"
          }
        }
      }
    },
    {
      "PutRequest": {
        "Item": {
          "cardId": {
            "S": "ed21d257-768c-4915-ae84-50c7823176af"
          },
          "player": {
            "S": "Drake Maye"
          },
          "card_name": {
            "S": "Drake Maye 2024 Phoenix #CON-DME Contours - Green"
          },
          "grade": {
            "S": "Raw"
          },
          "date": {
            "S": "20260207"
          },
          "price": {
            "N": "56.00"
          },
          "number_of_sales": {
            "N": "8"
          },
          "total_sales_amount": {
            "N": "966.50"
          },
          "price_change_percent": {
            "N": "-81.33"
          },
          "average_price": {
            "N": "120.81"
          },
          "volume_change_percent": {
            "N": "0.00"
          },
          "price_change_amount": {
            "N": "-244.00"
          },
          "max_sale_price": {
            "N": "300.00"
          },
          "min_sale_price": {
            "N": "56.00"
          },
          "last_sale_date": {
            "S": "09/17/2025"
          }
        }
      }
    },
    {
      "PutRequest": {
        "Item": {
          "cardId": {
            "S": "d1a94e37-336f-4ab2-8457-e77cb8101000"
          },
          "player": {
            "S": "Jonathon Brooks"
          },
          "card_name": {
            "S": "Jonathon Brooks 2024 Prizm Deca #46 FOTL Black Gold Shimmer"
          },
          "grade": {
            "S": "Raw"
          },
          "date": {
            "S": "20260207"
          },
          "price": {
            "N": "12.51"
          },
          "number_of_sales": {
            "N": "6"
          },
          "total_sales_amount": {
            "N": "220.01"
          },
          "price_change_percent": {
            "N": "-81.33"
          },
          "average_price": {
            "N": "36.67"
          },
          "volume_change_percent": {
            "N": "0.00"
          },
          "price_change_amount": {
            "N": "-54.49"
          },
          "max_sale_price": {
            "N": "67.00"
          },
          "min_sale_price": {
            "N": "12.51"
          },
          "last_sale_date": {
            "S": "10/20/2025"
          }
        }
      }
    },
    {
      "PutRequest": {
        "Item": {
          "cardId": {
            "S": "d49f0304-3e62-4431-b8d7-54e83f750fce"
          },
          "player": {
            "S": "Kate Martin"
          },
          "card_name": {
            "S": "Kate Martin 2024 Prizm WNBA #126 Blue"
          },
          "grade": {
            "S": "Raw"
          },
          "date": {
            "S": "20260207"
          },
          "price": {
            "N": "5.00"
          },
          "number_of_sales": {
            "N": "20"
          },
          "total_sales_amount": {
            "N": "266.97"
          },
          "price_change_percent": {
            "N": "-81.32"
          },
          "average_price": {
            "N": "13.35"
          },
          "volume_change_percent": {
            "N": "0.00"
          },
          "price_change_amount": {
            "N": "-21.77"
          },
          "max_sale_price": {
            "N": "31.01"
          },
          "min_sale_price": {
            "N": "3.50"
          },
          "last_sale_date": {
            "S": "11/04/2025"
          }
        }
      }
    },
    {
      "PutRequest": {
        "Item": {
          "cardId": {
            "S": "d8dc0192-3d69-45e8-a124-7d3a74d0da99"
          },
          "player": {
            "S": "Xavier Worthy"
          },
          "card_name": {
            "S": "Xavier Worthy 2024 Prizm Deca #7 Downtown Bound - Silver"
          },
          "grade": {
            "S": "Raw"
          },
          "date": {
            "S": "20260207"
          },
          "price": {
            "N": "2.80"
          },
          "number_of_sales": {
            "N": "18"
          },
          "total_sales_amount": {
            "N": "123.66"
          },
          "price_change_percent": {
            "N": "-81.32"
          },
          "average_price": {
            "N": "6.87"
          },
          "volume_change_percent": {
            "N": "0.00"
          },
          "price_change_amount": {
            "N": "-12.19"
          },
          "max_sale_price": {
            "N": "14.99"
          },
          "min_sale_price": {
            "N": "0.99"
          },
          "last_sale_date": {
            "S": "10/09/2025"
          }
        }
      }
    },
    {
      "PutRequest": {
        "Item": {
          "cardId": {
            "S": "d909a1a8-010b-4470-9d07-be5df3f7cda2"
          },
          "player": {
            "S": "Tyler Warren"
          },
          "card_name": {
            "S": "Tyler Warren 2025 Mosaic #25 Notoriety - Orange Fluorescent"
          },
          "grade": {
            "S": "Raw"
          },
          "date": {
            "S": "20260207"
          },
          "price": {
            "N": "2.99"
          },
          "number_of_sales": {
            "N": "135"
          },
          "total_sales_amount": {
            "N": "674.57"
          },
          "price_change_percent": {
            "N": "-81.31"
          },
          "average_price": {
            "N": "5.00"
          },
          "volume_change_percent": {
            "N": "0.00"
          },
          "price_change_amount": {
            "N": "-13.01"
          },
          "max_sale_price": {
            "N": "20.00"
          },
          "min_sale_price": {
            "N": "0.99"
          },
          "last_sale_date": {
            "S": "02/05/2026"
          }
        }
      }
    },
    {
      "PutRequest": {
        "Item": {
          "cardId": {
            "S": "cf12ee14-5379-4757-a7cf-e3aeef77eae5"
          },
          "player": {
            "S": "Jaylen Brown"
          },
          "card_name": {
            "S": "Jaylen Brown 2016 Revolution #107 Astro"
          },
          "grade": {
            "S": "Raw"
          },
          "date": {
            "S": "20260207"
          },
          "price": {
            "N": "2.99"
          },
          "number_of_sales": {
            "N": "9"
          },
          "total_sales_amount": {
            "N": "100.17"
          },
          "price_change_percent": {
            "N": "-81.31"
          },
          "average_price": {
            "N": "11.13"
          },
          "volume_change_percent": {
            "N": "-64.00"
          },
          "price_change_amount": {
            "N": "-13.01"
          },
          "max_sale_price": {
            "N": "16.00"
          },
          "min_sale_price": {
            "N": "2.99"
          },
          "last_sale_date": {
            "S": "01/31/2026"
          }
        }
      }
    },
    {
      "PutRequest": {
        "Item": {
          "cardId": {
            "S": "e8483d66-1444-4db6-8af4-647e7bd7b171"
          },
          "player": {
            "S": "Jalen Milroe"
          },
          "card_name": {
            "S": "Jalen Milroe 2025 Mosaic #322 Genesis"
          },
          "grade": {
            "S": "Raw"
          },
          "date": {
            "S": "20260207"
          },
          "price": {
            "N": "21.50"
          },
          "number_of_sales": {
            "N": "8"
          },
          "total_sales_amount": {
            "N": "728.99"
          },
          "price_change_percent": {
            "N": "-81.30"
          },
          "average_price": {
            "N": "91.12"
          },
          "volume_change_percent": {
            "N": "0.00"
          },
          "price_change_amount": {
            "N": "-93.50"
          },
          "max_sale_price": {
            "N": "117.50"
          },
          "min_sale_price": {
            "N": "21.50"
          },
          "last_sale_date": {
            "S": "01/07/2026"
          }
        }
      }
    },
    {
      "PutRequest": {
        "Item": {
          "cardId": {
            "S": "e9c8cc79-a8e2-4157-93a4-4df17b4868aa"
          },
          "player": {
            "S": "RJ Harvey"
          },
          "card_name": {
            "S": "RJ Harvey 2025 Mosaic #375 Blue Scope"
          },
          "grade": {
            "S": "Raw"
          },
          "date": {
            "S": "20260207"
          },
          "price": {
            "N": "1.12"
          },
          "number_of_sales": {
            "N": "12"
          },
          "total_sales_amount": {
            "N": "37.88"
          },
          "price_change_percent": {
            "N": "-81.30"
          },
          "average_price": {
            "N": "3.16"
          },
          "volume_change_percent": {
            "N": "0.00"
          },
          "price_change_amount": {
            "N": "-4.87"
          },
          "max_sale_price": {
            "N": "6.99"
          },
          "min_sale_price": {
            "N": "0.99"
          },
          "last_sale_date": {
            "S": "01/28/2026"
          }
        }
      }
    },
    {
      "PutRequest": {
        "Item": {
          "cardId": {
            "S": "804d0708-3a3e-4298-a9dd-edc459763ab7"
          },
          "player": {
            "S": "Tom Brady"
          },
          "card_name": {
            "S": "Tom Brady 2020 Mosaic #135 Base"
          },
          "grade": {
            "S": "Raw"
          },
          "date": {
            "S": "20260207"
          },
          "price": {
            "N": "1.87"
          },
          "number_of_sales": {
            "N": "61"
          },
          "total_sales_amount": {
            "N": "140.59"
          },
          "price_change_percent": {
            "N": "-81.30"
          },
          "average_price": {
            "N": "2.30"
          },
          "volume_change_percent": {
            "N": "24.49"
          },
          "price_change_amount": {
            "N": "-8.13"
          },
          "max_sale_price": {
            "N": "15.51"
          },
          "min_sale_price": {
            "N": "0.99"
          },
          "last_sale_date": {
            "S": "02/03/2026"
          }
        }
      }
    },
    {
      "PutRequest": {
        "Item": {
          "cardId": {
            "S": "76e66abe-debf-46ae-90c3-45ea91dd81ef"
          },
          "player": {
            "S": "Bryce Young"
          },
          "card_name": {
            "S": "Bryce Young 2023 Rookies & Stars #CR-5 Crusade"
          },
          "grade": {
            "S": "Raw"
          },
          "date": {
            "S": "20260207"
          },
          "price": {
            "N": "1.16"
          },
          "number_of_sales": {
            "N": "40"
          },
          "total_sales_amount": {
            "N": "126.79"
          },
          "price_change_percent": {
            "N": "-81.30"
          },
          "average_price": {
            "N": "3.17"
          },
          "volume_change_percent": {
            "N": "-75.16"
          },
          "price_change_amount": {
            "N": "-5.06"
          },
          "max_sale_price": {
            "N": "15.00"
          },
          "min_sale_price": {
            "N": "0.99"
          },
          "last_sale_date": {
            "S": "01/24/2026"
          }
        }
      }
    },
    {
      "PutRequest": {
        "Item": {
          "cardId": {
            "S": "c50d2024-10b2-4664-a995-1aba7a3da8ba"
          },
          "player": {
            "S": "Matas Buzelis"
          },
          "card_name": {
            "S": "Matas Buzelis 2024 Optic #271 Aqua"
          },
          "grade": {
            "S": "Raw"
          },
          "date": {
            "S": "20260207"
          },
          "price": {
            "N": "10.50"
          },
          "number_of_sales": {
            "N": "9"
          },
          "total_sales_amount": {
            "N": "209.94"
          },
          "price_change_percent": {
            "N": "-81.30"
          },
          "average_price": {
            "N": "23.33"
          },
          "volume_change_percent": {
            "N": "0.00"
          },
          "price_change_amount": {
            "N": "-45.64"
          },
          "max_sale_price": {
            "N": "56.14"
          },
          "min_sale_price": {
            "N": "9.50"
          },
          "last_sale_date": {
            "S": "01/20/2026"
          }
        }
      }
    },
    {
      "PutRequest": {
        "Item": {
          "cardId": {
            "S": "b5655f3e-7f05-4f9c-b07a-5e454470e71d"
          },
          "player": {
            "S": "Shai Gilgeous-Alexander"
          },
          "card_name": {
            "S": "Shai Gilgeous-Alexander 2025 Topps #115 Wood"
          },
          "grade": {
            "S": "Raw"
          },
          "date": {
            "S": "20260207"
          },
          "price": {
            "N": "108.50"
          },
          "number_of_sales": {
            "N": "5"
          },
          "total_sales_amount": {
            "N": "1241.87"
          },
          "price_change_percent": {
            "N": "-81.29"
          },
          "average_price": {
            "N": "248.37"
          },
          "volume_change_percent": {
            "N": "0.00"
          },
          "price_change_amount": {
            "N": "-471.50"
          },
          "max_sale_price": {
            "N": "580.00"
          },
          "min_sale_price": {
            "N": "103.37"
          },
          "last_sale_date": {
            "S": "01/24/2026"
          }
        }
      }
    },
    {
      "PutRequest": {
        "Item": {
          "cardId": {
            "S": "460cb202-c170-44c9-b960-a102748cabfa"
          },
          "player": {
            "S": "Trevor Lawrence"
          },
          "card_name": {
            "S": "Trevor Lawrence 2024 Mosaic #99 Red Sparkle"
          },
          "grade": {
            "S": "Raw"
          },
          "date": {
            "S": "20260207"
          },
          "price": {
            "N": "3.95"
          },
          "number_of_sales": {
            "N": "12"
          },
          "total_sales_amount": {
            "N": "81.40"
          },
          "price_change_percent": {
            "N": "-81.29"
          },
          "average_price": {
            "N": "6.78"
          },
          "volume_change_percent": {
            "N": "0.00"
          },
          "price_change_amount": {
            "N": "-17.16"
          },
          "max_sale_price": {
            "N": "21.11"
          },
          "min_sale_price": {
            "N": "2.50"
          },
          "last_sale_date": {
            "S": "02/03/2026"
          }
        }
      }
    }
  ]
}