{
  "sports-card-capstone-card-data": [
    {
      "PutRequest": {
        "Item": {
          "cardId": {
            "S": "53aa1689-5f58-434a-9f65-7bef0f57de00"
          },
          "player": {
            "S": "Jalen Williams"
          },
          "card_name": {
            "S": "Jalen Williams 2022 Donruss #212 Base"
          },
          "grade": {
            "S": "Raw"
          },
          "date": {
            "S": "20260210"
          },
          "price": {
            "N": "0.99"
          },
          "number_of_sales": {
            "N": "6"
          },
          "total_sales_amount": {
            "N": "8.53"
          },
          "price_change_percent": {
            "N": "-34.35"
          },
          "average_price": {
            "N": "1.42"
          },
          "volume_change_percent": {
            "N": "200.00"
          },
          "price_change_amount": {
            "N": "-0.52"
          },
          "max_sale_price": {
            "N": "1.99"
          },
          "min_sale_price": {
            "N": "0.99"
          },
          "last_sale_date": {
            "S": "02/09/2026"
          }
        }
      }
    },
    {
      "PutRequest": {
        "Item": {
          "cardId": {
            "S": "d3b67140-691b-4617-8091-8f64219bcb2e"
          },
          "player": {
            "S": "Michael Jordan"
          },
          "card_name": {
            "S": "Michael Jordan 1993 Upper Deck #204 NBA Finals Highlights (1993 NBA Finals MVP\")\""
          },
          "grade": {
            "S": "Raw"
          },
          "date": {
            "S": "20260210"
          },
          "price": {
            "N": "1.49"
          },
          "number_of_sales": {
            "N": "16"
          },
          "total_sales_amount": {
            "N": "43.99"
          },
          "price_change_percent": {
            "N": "-34.36"
          },
          "average_price": {
            "N": "2.75"
          },
          "volume_change_percent": {
            "N": "6.67"
          },
          "price_change_amount": {
            "N": "-0.78"
          },
          "max_sale_price": {
            "N": "9.00"
          },
          "min_sale_price": {
            "N": "1.00"
          },
          "last_sale_date": {
            "S": "02/09/2026"
          }
        }
      }
    },
    {
      "PutRequest": {
        "Item": {
          "cardId": {
            "S": "56b3e2cc-eeb4-4b5e-95d6-373cada610fe"
          },
          "player": {
            "S": "Shedeur Sanders"
          },
          "card_name": {
            "S": "Shedeur Sanders 2025 Mosaic #290 Rookie Variation - Green"
          },
          "grade": {
            "S": "Raw"
          },
          "date": {
            "S": "20260210"
          },
          "price": {
            "N": "2.63"
          },
          "number_of_sales": {
            "N": "9"
          },
          "total_sales_amount": {
            "N": "30.26"
          },
          "price_change_percent": {
            "N": "-34.38"
          },
          "average_price": {
            "N": "3.36"
          },
          "volume_change_percent": {
            "N": "28.57"
          },
          "price_change_amount": {
            "N": "-1.38"
          },
          "max_sale_price": {
            "N": "5.00"
          },
          "min_sale_price": {
            "N": "2.00"
          },
          "last_sale_date": {
            "S": "02/09/2026"
          }
        }
      }
    },
    {
      "PutRequest": {
        "Item": {
          "cardId": {
            "S": "b49c9a26-d6f5-4744-93e5-85fab641d99d"
          },
          "player": {
            "S": "Quinn Ewers"
          },
          "card_name": {
            "S": "Quinn Ewers 2025 Prizm #425 Rookie Variation - Silver"
          },
          "grade": {
            "S": "Raw"
          },
          "date": {
            "S": "20260210"
          },
          "price": {
            "N": "11.00"
          },
          "number_of_sales": {
            "N": "12"
          },
          "total_sales_amount": {
            "N": "158.54"
          },
          "price_change_percent": {
            "N": "-34.38"
          },
          "average_price": {
            "N": "13.21"
          },
          "volume_change_percent": {
            "N": "20.00"
          },
          "price_change_amount": {
            "N": "-5.76"
          },
          "max_sale_price": {
            "N": "19.50"
          },
          "min_sale_price": {
            "N": "6.99"
          },
          "last_sale_date": {
            "S": "02/09/2026"
          }
        }
      }
    },
    {
      "PutRequest": {
        "Item": {
          "cardId": {
            "S": "38f0a167-3e60-4bfb-a1bc-65885192635f"
          },
          "player": {
            "S": "Cam Skattebo"
          },
          "card_name": {
            "S": "Cam Skattebo 2025 Prizm Draft Picks #9 Base"
          },
          "grade": {
            "S": "Raw"
          },
          "date": {
            "S": "20260210"
          },
          "price": {
            "N": "1.56"
          },
          "number_of_sales": {
            "N": "8"
          },
          "total_sales_amount": {
            "N": "13.87"
          },
          "price_change_percent": {
            "N": "-34.39"
          },
          "average_price": {
            "N": "1.73"
          },
          "volume_change_percent": {
            "N": "-11.11"
          },
          "price_change_amount": {
            "N": "-0.81"
          },
          "max_sale_price": {
            "N": "3.00"
          },
          "min_sale_price": {
            "N": "0.99"
          },
          "last_sale_date": {
            "S": "02/09/2026"
          }
        }
      }
    },
    {
      "PutRequest": {
        "Item": {
          "cardId": {
            "S": "d1dc6883-6d25-4f74-8110-08477affed38"
          },
          "player": {
            "S": "Drake Maye"
          },
          "card_name": {
            "S": "Drake Maye 2024 Mosaic #20 Kaleidoscopic"
          },
          "grade": {
            "S": "Raw"
          },
          "date": {
            "S": "20260210"
          },
          "price": {
            "N": "200.00"
          },
          "number_of_sales": {
            "N": "7"
          },
          "total_sales_amount": {
            "N": "1764.90"
          },
          "price_change_percent": {
            "N": "-34.43"
          },
          "average_price": {
            "N": "252.13"
          },
          "volume_change_percent": {
            "N": "250.00"
          },
          "price_change_amount": {
            "N": "-105.00"
          },
          "max_sale_price": {
            "N": "305.00"
          },
          "min_sale_price": {
            "N": "200.00"
          },
          "last_sale_date": {
            "S": "02/09/2026"
          }
        }
      }
    },
    {
      "PutRequest": {
        "Item": {
          "cardId": {
            "S": "616f6af0-df7d-40d6-a482-74135d8ff673"
          },
          "player": {
            "S": "Jaxson Dart"
          },
          "card_name": {
            "S": "Jaxson Dart 2025 Rookies & Stars #11 Crusade - Red Plaid"
          },
          "grade": {
            "S": "Raw"
          },
          "date": {
            "S": "20260210"
          },
          "price": {
            "N": "9.50"
          },
          "number_of_sales": {
            "N": "10"
          },
          "total_sales_amount": {
            "N": "137.00"
          },
          "price_change_percent": {
            "N": "-34.48"
          },
          "average_price": {
            "N": "13.70"
          },
          "volume_change_percent": {
            "N": "-9.09"
          },
          "price_change_amount": {
            "N": "-5.00"
          },
          "max_sale_price": {
            "N": "17.00"
          },
          "min_sale_price": {
            "N": "6.50"
          },
          "last_sale_date": {
            "S": "02/08/2026"
          }
        }
      }
    },
    {
      "PutRequest": {
        "Item": {
          "cardId": {
            "S": "1c3e675a-9178-46a2-9efd-d7cb1a9793f1"
          },
          "player": {
            "S": "Maxime Raynaud"
          },
          "card_name": {
            "S": "Maxime Raynaud 2025 Topps Chrome #293 X-Fractor"
          },
          "grade": {
            "S": "Raw"
          },
          "date": {
            "S": "20260210"
          },
          "price": {
            "N": "1.99"
          },
          "number_of_sales": {
            "N": "29"
          },
          "total_sales_amount": {
            "N": "58.79"
          },
          "price_change_percent": {
            "N": "-34.50"
          },
          "average_price": {
            "N": "2.03"
          },
          "volume_change_percent": {
            "N": "-32.56"
          },
          "price_change_amount": {
            "N": "-1.05"
          },
          "max_sale_price": {
            "N": "5.00"
          },
          "min_sale_price": {
            "N": "0.99"
          },
          "last_sale_date": {
            "S": "02/09/2026"
          }
        }
      }
    },
    {
      "PutRequest": {
        "Item": {
          "cardId": {
            "S": "99d2e06f-967f-43e9-9321-83f4fce097d8"
          },
          "player": {
            "S": "Drake Maye"
          },
          "card_name": {
            "S": "Drake Maye 2024 Select #113 Premier Level Red & Blue Shock"
          },
          "grade": {
            "S": "Raw"
          },
          "date": {
            "S": "20260210"
          },
          "price": {
            "N": "31.00"
          },
          "number_of_sales": {
            "N": "29"
          },
          "total_sales_amount": {
            "N": "867.89"
          },
          "price_change_percent": {
            "N": "-34.51"
          },
          "average_price": {
            "N": "29.93"
          },
          "volume_change_percent": {
            "N": "3.57"
          },
          "price_change_amount": {
            "N": "-16.33"
          },
          "max_sale_price": {
            "N": "60.00"
          },
          "min_sale_price": {
            "N": "11.49"
          },
          "last_sale_date": {
            "S": "02/09/2026"
          }
        }
      }
    },
    {
      "PutRequest": {
        "Item": {
          "cardId": {
            "S": "02038d09-0e98-4985-892c-8421f0bb61a8"
          },
          "player": {
            "S": "Fernando Mendoza"
          },
          "card_name": {
            "S": "Fernando Mendoza 2025 Bowman U Now #26 Base (Print Run: 2,475)"
          },
          "grade": {
            "S": "Raw"
          },
          "date": {
            "S": "20260210"
          },
          "price": {
            "N": "10.97"
          },
          "number_of_sales": {
            "N": "27"
          },
          "total_sales_amount": {
            "N": "369.58"
          },
          "price_change_percent": {
            "N": "-34.51"
          },
          "average_price": {
            "N": "13.69"
          },
          "volume_change_percent": {
            "N": "-12.90"
          },
          "price_change_amount": {
            "N": "-5.78"
          },
          "max_sale_price": {
            "N": "29.99"
          },
          "min_sale_price": {
            "N": "6.49"
          },
          "last_sale_date": {
            "S": "02/09/2026"
          }
        }
      }
    },
    {
      "PutRequest": {
        "Item": {
          "cardId": {
            "S": "f9492c42-ba9a-4f40-bd9c-75f669800129"
          },
          "player": {
            "S": "Victor Wembanyama"
          },
          "card_name": {
            "S": "Victor Wembanyama 2023 Prizm #3 Instant Impact"
          },
          "grade": {
            "S": "Raw"
          },
          "date": {
            "S": "20260210"
          },
          "price": {
            "N": "3.60"
          },
          "number_of_sales": {
            "N": "18"
          },
          "total_sales_amount": {
            "N": "97.59"
          },
          "price_change_percent": {
            "N": "-34.52"
          },
          "average_price": {
            "N": "5.42"
          },
          "volume_change_percent": {
            "N": "-25.00"
          },
          "price_change_amount": {
            "N": "-1.90"
          },
          "max_sale_price": {
            "N": "17.50"
          },
          "min_sale_price": {
            "N": "1.31"
          },
          "last_sale_date": {
            "S": "02/08/2026"
          }
        }
      }
    },
    {
      "PutRequest": {
        "Item": {
          "cardId": {
            "S": "9a5d4881-e7e6-4ab6-9ef8-466017b4b280"
          },
          "player": {
            "S": "Kobe Bryant"
          },
          "card_name": {
            "S": "Kobe Bryant 1996 Topps Stadium Club #R12 Rookies 1"
          },
          "grade": {
            "S": "Raw"
          },
          "date": {
            "S": "20260210"
          },
          "price": {
            "N": "17.50"
          },
          "number_of_sales": {
            "N": "10"
          },
          "total_sales_amount": {
            "N": "228.87"
          },
          "price_change_percent": {
            "N": "-34.54"
          },
          "average_price": {
            "N": "22.89"
          },
          "volume_change_percent": {
            "N": "0.00"
          },
          "price_change_amount": {
            "N": "-9.23"
          },
          "max_sale_price": {
            "N": "41.25"
          },
          "min_sale_price": {
            "N": "16.00"
          },
          "last_sale_date": {
            "S": "02/08/2026"
          }
        }
      }
    },
    {
      "PutRequest": {
        "Item": {
          "cardId": {
            "S": "acafb790-12b5-4bdd-a64c-09848a905b69"
          },
          "player": {
            "S": "Jaxson Dart"
          },
          "card_name": {
            "S": "Jaxson Dart 2025 Rookies & Stars #10 Stellar Rookies - Red Plaid"
          },
          "grade": {
            "S": "Raw"
          },
          "date": {
            "S": "20260210"
          },
          "price": {
            "N": "8.50"
          },
          "number_of_sales": {
            "N": "7"
          },
          "total_sales_amount": {
            "N": "77.98"
          },
          "price_change_percent": {
            "N": "-34.57"
          },
          "average_price": {
            "N": "11.14"
          },
          "volume_change_percent": {
            "N": "0.00"
          },
          "price_change_amount": {
            "N": "-4.49"
          },
          "max_sale_price": {
            "N": "13.50"
          },
          "min_sale_price": {
            "N": "8.00"
          },
          "last_sale_date": {
            "S": "02/09/2026"
          }
        }
      }
    },
    {
      "PutRequest": {
        "Item": {
          "cardId": {
            "S": "e0fac8be-7f74-4f5f-a76f-7e6188305c22"
          },
          "player": {
            "S": "Drake Maye"
          },
          "card_name": {
            "S": "Drake Maye 2024 Phoenix #179 Silver"
          },
          "grade": {
            "S": "Raw"
          },
          "date": {
            "S": "20260210"
          },
          "price": {
            "N": "8.50"
          },
          "number_of_sales": {
            "N": "15"
          },
          "total_sales_amount": {
            "N": "82.83"
          },
          "price_change_percent": {
            "N": "-34.59"
          },
          "average_price": {
            "N": "5.52"
          },
          "volume_change_percent": {
            "N": "-34.78"
          },
          "price_change_amount": {
            "N": "-4.50"
          },
          "max_sale_price": {
            "N": "20.00"
          },
          "min_sale_price": {
            "N": "0.99"
          },
          "last_sale_date": {
            "S": "02/09/2026"
          }
        }
      }
    },
    {
      "PutRequest": {
        "Item": {
          "cardId": {
            "S": "795a701d-4f02-4dbd-9284-c19e71e3e93b"
          },
          "player": {
            "S": "Jared McCain"
          },
          "card_name": {
            "S": "Jared McCain 2024 Prizm #222 Ice"
          },
          "grade": {
            "S": "Raw"
          },
          "date": {
            "S": "20260210"
          },
          "price": {
            "N": "3.26"
          },
          "number_of_sales": {
            "N": "5"
          },
          "total_sales_amount": {
            "N": "16.78"
          },
          "price_change_percent": {
            "N": "-34.60"
          },
          "average_price": {
            "N": "3.36"
          },
          "volume_change_percent": {
            "N": "150.00"
          },
          "price_change_amount": {
            "N": "-1.73"
          },
          "max_sale_price": {
            "N": "5.00"
          },
          "min_sale_price": {
            "N": "1.79"
          },
          "last_sale_date": {
            "S": "02/06/2026"
          }
        }
      }
    },
    {
      "PutRequest": {
        "Item": {
          "cardId": {
            "S": "5079f34f-52c8-461d-822e-eba6c9ce6f10"
          },
          "player": {
            "S": "Jaxson Dart"
          },
          "card_name": {
            "S": "Jaxson Dart 2025 Elite #103 Green Disco"
          },
          "grade": {
            "S": "Raw"
          },
          "date": {
            "S": "20260210"
          },
          "price": {
            "N": "8.50"
          },
          "number_of_sales": {
            "N": "9"
          },
          "total_sales_amount": {
            "N": "149.48"
          },
          "price_change_percent": {
            "N": "-34.62"
          },
          "average_price": {
            "N": "16.61"
          },
          "volume_change_percent": {
            "N": "800.00"
          },
          "price_change_amount": {
            "N": "-4.50"
          },
          "max_sale_price": {
            "N": "27.99"
          },
          "min_sale_price": {
            "N": "7.50"
          },
          "last_sale_date": {
            "S": "02/08/2026"
          }
        }
      }
    },
    {
      "PutRequest": {
        "Item": {
          "cardId": {
            "S": "6a8215e4-ef87-48f2-8feb-437f5ba4000d"
          },
          "player": {
            "S": "Nick Emmanwori"
          },
          "card_name": {
            "S": "Nick Emmanwori 2025 Prizm #320 White Disco"
          },
          "grade": {
            "S": "Raw"
          },
          "date": {
            "S": "20260210"
          },
          "price": {
            "N": "4.17"
          },
          "number_of_sales": {
            "N": "24"
          },
          "total_sales_amount": {
            "N": "133.94"
          },
          "price_change_percent": {
            "N": "-34.64"
          },
          "average_price": {
            "N": "5.58"
          },
          "volume_change_percent": {
            "N": "4.35"
          },
          "price_change_amount": {
            "N": "-2.21"
          },
          "max_sale_price": {
            "N": "10.00"
          },
          "min_sale_price": {
            "N": "1.25"
          },
          "last_sale_date": {
            "S": "02/08/2026"
          }
        }
      }
    },
    {
      "PutRequest": {
        "Item": {
          "cardId": {
            "S": "04cd110b-8bc0-4519-9f75-788b4b95fab6"
          },
          "player": {
            "S": "Jason Williams"
          },
          "card_name": {
            "S": "Jason Williams 1998 Topps #153 Base"
          },
          "grade": {
            "S": "Raw"
          },
          "date": {
            "S": "20260210"
          },
          "price": {
            "N": "1.95"
          },
          "number_of_sales": {
            "N": "9"
          },
          "total_sales_amount": {
            "N": "21.57"
          },
          "price_change_percent": {
            "N": "-34.67"
          },
          "average_price": {
            "N": "2.40"
          },
          "volume_change_percent": {
            "N": "-30.77"
          },
          "price_change_amount": {
            "N": "-1.04"
          },
          "max_sale_price": {
            "N": "3.25"
          },
          "min_sale_price": {
            "N": "1.80"
          },
          "last_sale_date": {
            "S": "02/09/2026"
          }
        }
      }
    },
    {
      "PutRequest": {
        "Item": {
          "cardId": {
            "S": "e56f116b-e3d7-44a9-a914-d4bd9a51411b"
          },
          "player": {
            "S": "Jaxon Smith-Njigba"
          },
          "card_name": {
            "S": "Jaxon Smith-Njigba 2023 Select #87 Concourse Silver Die-Cut"
          },
          "grade": {
            "S": "Raw"
          },
          "date": {
            "S": "20260210"
          },
          "price": {
            "N": "3.00"
          },
          "number_of_sales": {
            "N": "19"
          },
          "total_sales_amount": {
            "N": "93.69"
          },
          "price_change_percent": {
            "N": "-34.68"
          },
          "average_price": {
            "N": "4.93"
          },
          "volume_change_percent": {
            "N": "11.76"
          },
          "price_change_amount": {
            "N": "-1.59"
          },
          "max_sale_price": {
            "N": "8.50"
          },
          "min_sale_price": {
            "N": "0.99"
          },
          "last_sale_date": {
            "S": "02/09/2026"
          }
        }
      }
    },
    {
      "PutRequest": {
        "Item": {
          "cardId": {
            "S": "33034de1-17d0-4cff-8aba-6c6a8aaa1e3e"
          },
          "player": {
            "S": "Michael Jordan"
          },
          "card_name": {
            "S": "Michael Jordan 1989 Fleer #3 Stickers"
          },
          "grade": {
            "S": "PSA 8"
          },
          "date": {
            "S": "20260210"
          },
          "price": {
            "N": "34.61"
          },
          "number_of_sales": {
            "N": "7"
          },
          "total_sales_amount": {
            "N": "299.20"
          },
          "price_change_percent": {
            "N": "-34.68"
          },
          "average_price": {
            "N": "42.74"
          },
          "volume_change_percent": {
            "N": "40.00"
          },
          "price_change_amount": {
            "N": "-18.38"
          },
          "max_sale_price": {
            "N": "52.99"
          },
          "min_sale_price": {
            "N": "32.23"
          },
          "last_sale_date": {
            "S": "02/08/2026"
          }
        }
      }
    },
    {
      "PutRequest": {
        "Item": {
          "cardId": {
            "S": "20d4a3df-389a-4f48-b20b-1c0c597390f1"
          },
          "player": {
            "S": "Tyrese Maxey"
          },
          "card_name": {
            "S": "Tyrese Maxey 2025 Topps Chrome #185 Image Variation"
          },
          "grade": {
            "S": "Raw"
          },
          "date": {
            "S": "20260210"
          },
          "price": {
            "N": "7.83"
          },
          "number_of_sales": {
            "N": "5"
          },
          "total_sales_amount": {
            "N": "40.99"
          },
          "price_change_percent": {
            "N": "-34.72"
          },
          "average_price": {
            "N": "8.20"
          },
          "volume_change_percent": {
            "N": "0.00"
          },
          "price_change_amount": {
            "N": "-4.17"
          },
          "max_sale_price": {
            "N": "12.00"
          },
          "min_sale_price": {
            "N": "5.49"
          },
          "last_sale_date": {
            "S": "02/08/2026"
          }
        }
      }
    },
    {
      "PutRequest": {
        "Item": {
          "cardId": {
            "S": "0132d9bf-1a45-4c73-b94d-39c312ffa37d"
          },
          "player": {
            "S": "Drake Maye"
          },
          "card_name": {
            "S": "Drake Maye 2024 Donruss #18 Rookie Revolution"
          },
          "grade": {
            "S": "Raw"
          },
          "date": {
            "S": "20260210"
          },
          "price": {
            "N": "3.92"
          },
          "number_of_sales": {
            "N": "25"
          },
          "total_sales_amount": {
            "N": "148.36"
          },
          "price_change_percent": {
            "N": "-34.72"
          },
          "average_price": {
            "N": "5.93"
          },
          "volume_change_percent": {
            "N": "25.00"
          },
          "price_change_amount": {
            "N": "-2.08"
          },
          "max_sale_price": {
            "N": "22.67"
          },
          "min_sale_price": {
            "N": "1.25"
          },
          "last_sale_date": {
            "S": "02/08/2026"
          }
        }
      }
    },
    {
      "PutRequest": {
        "Item": {
          "cardId": {
            "S": "52386791-d1da-4125-8277-be5e72a9be5c"
          },
          "player": {
            "S": "Drake Maye"
          },
          "card_name": {
            "S": "Drake Maye 2024 Select #3 Select Certified Rookies"
          },
          "grade": {
            "S": "Raw"
          },
          "date": {
            "S": "20260210"
          },
          "price": {
            "N": "3.66"
          },
          "number_of_sales": {
            "N": "202"
          },
          "total_sales_amount": {
            "N": "945.89"
          },
          "price_change_percent": {
            "N": "-34.76"
          },
          "average_price": {
            "N": "4.68"
          },
          "volume_change_percent": {
            "N": "-6.48"
          },
          "price_change_amount": {
            "N": "-1.95"
          },
          "max_sale_price": {
            "N": "12.50"
          },
          "min_sale_price": {
            "N": "0.99"
          },
          "last_sale_date": {
            "S": "02/09/2026"
          }
        }
      }
    },
    {
      "PutRequest": {
        "Item": {
          "cardId": {
            "S": "c1130579-949a-4d0e-b6bd-29174f990010"
          },
          "player": {
            "S": "Cooper Flagg"
          },
          "card_name": {
            "S": "Cooper Flagg 2025 Topps #8B-31 8-Bit Ballers"
          },
          "grade": {
            "S": "Raw"
          },
          "date": {
            "S": "20260210"
          },
          "price": {
            "N": "2.70"
          },
          "number_of_sales": {
            "N": "322"
          },
          "total_sales_amount": {
            "N": "1037.08"
          },
          "price_change_percent": {
            "N": "-34.76"
          },
          "average_price": {
            "N": "3.22"
          },
          "volume_change_percent": {
            "N": "49.07"
          },
          "price_change_amount": {
            "N": "-1.44"
          },
          "max_sale_price": {
            "N": "19.99"
          },
          "min_sale_price": {
            "N": "0.99"
          },
          "last_sale_date": {
            "S": "02/09/2026"
          }
        }
      }
    },
    {
      "PutRequest": {
        "Item": {
          "cardId": {
            "S": "3bb4dff6-1f3d-49bb-8742-25633ec05f7d"
          },
          "player": {
            "S": "Tyrese Maxey"
          },
          "card_name": {
            "S": "Tyrese Maxey 2020 Prizm #256 Silver"
          },
          "grade": {
            "S": "Raw"
          },
          "date": {
            "S": "20260210"
          },
          "price": {
            "N": "30.00"
          },
          "number_of_sales": {
            "N": "13"
          },
          "total_sales_amount": {
            "N": "461.48"
          },
          "price_change_percent": {
            "N": "-34.78"
          },
          "average_price": {
            "N": "35.50"
          },
          "volume_change_percent": {
            "N": "30.00"
          },
          "price_change_amount": {
            "N": "-16.00"
          },
          "max_sale_price": {
            "N": "46.00"
          },
          "min_sale_price": {
            "N": "20.50"
          },
          "last_sale_date": {
            "S": "02/09/2026"
          }
        }
      }
    }
  ]
}